Metadata-Version: 1.0
Name: dvdfingerprint
Version: 0.1.3
Summary: A DVD Fingerprint Geneator
Home-page: https://github.com/kolanos/dvdfingerprint
Author: Michael Lavers
Author-email: kolanos@gmail.com
License: BSD
Platform: UNKNOWN
